gb_rotate/__init__.py
gb_rotate/gb_rotate.py
gb_rotate/main.py
gb_rotate-0.1.4.dist-info/LICENSE
gb_rotate-0.1.4.dist-info/METADATA
gb_rotate-0.1.4.dist-info/WHEEL
gb_rotate-0.1.4.dist-info/entry_points.txt
gb_rotate-0.1.4.dist-info/top_level.txt
gb_rotate-0.1.4.dist-info/RECORD
