Metadata-Version: 2.1
Name: gb_rotate
Version: 0.1.4
Summary: A command-line utility to rotate and reverse complement GenBank files.
Author-email: "Katie E. Herron" <kherronism@gmail.com>
Maintainer-email: "Katie E. Herron" <kherronism@gmail.com>
License: MIT License
Project-URL: Homepage, https://github.com/kherronism/gb_rotate
Keywords: genbank,bioinformatics,sequence,rotation,reverse-complement
Classifier: Development Status :: 4 - Beta
Classifier: Intended Audience :: Science/Research
Classifier: Programming Language :: Python :: 3
Classifier: License :: OSI Approved :: MIT License
Classifier: Operating System :: OS Independent
Requires-Python: >=3.8
License-File: LICENSE
Requires-Dist: typer
